[
  {
    "username": "nrusted0",
    "email": "kdelaeglise0@chicagotribune.com",
    "password": "iT0=STu|"
  },
  {
    "username": "rmacek1",
    "email": "jsessions1@nbcnews.com",
    "password": "eX3.H\"_#wHwsEF#"
  },
  {
    "username": "lfranzman2",
    "email": "ncasford2@xrea.com",
    "password": "dB0/Lk8uI"
  },
  {
    "username": "tschultheiss3",
    "email": "cklauber3@independent.co.uk",
    "password": "aM3+8*Ei?q?"
  },
  {
    "username": "cdubois4",
    "email": "swebster4@tripod.com",
    "password": "xH3&O>oZk4tN*IC"
  },
  {
    "username": "rfanti5",
    "email": "kbrookwood5@disqus.com",
    "password": "zP7<?OD@16"
  },
  {
    "username": "alias6",
    "email": "eboobier6@nasa.gov",
    "password": "uG5?(/,l)Wpmk8IE"
  },
  {
    "username": "hmcfee7",
    "email": "ebrookhouse7@comsenz.com",
    "password": "wG9<DW1=Xg4P3\\lL"
  },
  {
    "username": "dashburne8",
    "email": "mcartmer8@yale.edu",
    "password": "tP3\\(`$_O9<24"
  },
  {
    "username": "sdrewson9",
    "email": "ctearney9@auda.org.au",
    "password": "rI4=!=Kw!&,=,"
  }
]
